Metadata-Version: 2.1
Name: thispersondoesnotexist
Version: 1.0.2
Summary: API to thispersondoesnotexist.com
Home-page: https://github.com/makeev/ThisPersonDoesNotExistAPI
Author: MM
Author-email: mihail.makeev@gmail.com
License: UNKNOWN
Platform: UNKNOWN
Classifier: Programming Language :: Python :: 3
Classifier: License :: OSI Approved :: MIT License
Classifier: Operating System :: OS Independent
Requires-Python: >=3.6
